{
  "animateLoading": true,
  "borderRadius": "{{appsmith.theme.borderRadius.appBorderRadius}}",
  "bottomRow": 9,
  "dynamicBindingPathList": [
    {
      "key": "truncateButtonColor"
    },
    {
      "key": "fontFamily"
    },
    {
      "key": "borderRadius"
    }
  ],
  "dynamicHeight": "AUTO_HEIGHT",
  "dynamicTriggerPathList": [],
  "fontFamily": "{{appsmith.theme.fontFamily.appFont}}",
  "fontSize": "1.25rem",
  "fontStyle": "BOLD",
  "isLoading": false,
  "isVisible": true,
  "key": "fmbq1p4nh7",
  "leftColumn": 0,
  "maxDynamicHeight": 9000,
  "minDynamicHeight": 4,
  "minWidth": 450,
  "mobileBottomRow": 24,
  "mobileLeftColumn": 2,
  "mobileRightColumn": 18,
  "mobileTopRow": 20,
  "needsErrorInfo": false,
  "originalBottomRow": 22,
  "originalTopRow": 11,
  "overflow": "NONE",
  "parentColumnSpace": 6.84375,
  "parentId": "wfpy9zv9ex",
  "parentRowSpace": 10,
  "renderMode": "CANVAS",
  "responsiveBehavior": "fill",
  "rightColumn": 64,
  "shouldTruncate": false,
  "text": "Yapımcı: bettagroupTR",
  "textAlign": "CENTER",
  "textColor": "#f4f4f5",
  "topRow": 5,
  "truncateButtonColor": "{{appsmith.theme.colors.primaryColor}}",
  "type": "TEXT_WIDGET",
  "version": 1,
  "widgetId": "vxhri8j2dw",
  "widgetName": "Text3"
}